viewtext/__init__.py
viewtext/_version.py
viewtext/cli.py
viewtext/engine.py
viewtext/formatters.py
viewtext/loader.py
viewtext/registry.py
viewtext/registry_builder.py
viewtext/validator.py
viewtext-0.4.1.dist-info/licenses/LICENSE
viewtext-0.4.1.dist-info/METADATA
viewtext-0.4.1.dist-info/WHEEL
viewtext-0.4.1.dist-info/entry_points.txt
viewtext-0.4.1.dist-info/top_level.txt
viewtext-0.4.1.dist-info/RECORD
